README.md
setup.py
pinda/__init__.py
pinda/_version.py
pinda/commands.py
pinda/data.py
pinda/utilities.py
pinda.egg-info/PKG-INFO
pinda.egg-info/SOURCES.txt
pinda.egg-info/dependency_links.txt
pinda.egg-info/requires.txt
pinda.egg-info/top_level.txt
scripts/pinda
test/__init__.py
test/test_commands.py
test/test_utilities.py