Metadata-Version: 2.1
Name: pinda
Version: 0.1.1
Summary: Pip-INstallable Dockerized Applications
Home-page: https://bitbucket.org/claughton/pinda
Author: Charlie Laughton
Author-email: charles.laughton@nottingham.ac.uk
License: UNKNOWN
Platform: UNKNOWN
Classifier: Programming Language :: Python :: 3
Classifier: License :: OSI Approved :: BSD License
Classifier: Development Status :: 3 - Alpha
